gammarers/aws_secure_cloudfront_origin_bucket/__init__.py
gammarers/aws_secure_cloudfront_origin_bucket/py.typed
gammarers/aws_secure_cloudfront_origin_bucket/_jsii/__init__.py
gammarers/aws_secure_cloudfront_origin_bucket/_jsii/aws-secure-cloudfront-origin-bucket@2.1.22.jsii.tgz
gammarers_aws_secure_cloudfront_origin_bucket-2.1.22.dist-info/LICENSE
gammarers_aws_secure_cloudfront_origin_bucket-2.1.22.dist-info/METADATA
gammarers_aws_secure_cloudfront_origin_bucket-2.1.22.dist-info/WHEEL
gammarers_aws_secure_cloudfront_origin_bucket-2.1.22.dist-info/top_level.txt
gammarers_aws_secure_cloudfront_origin_bucket-2.1.22.dist-info/RECORD
