Metadata-Version: 2.1
Name: gammarers.aws-secure-cloudfront-origin-bucket
Version: 2.1.22
Summary: AWS CloudFront distribution origin S3 bucket.
Home-page: https://github.com/gammarers/aws-secure-cloudfront-origin-bucket.git
Author: yicr<yicr@users.noreply.github.com>
License: Apache-2.0
Project-URL: Source, https://github.com/gammarers/aws-secure-cloudfront-origin-bucket.git
Classifier: Intended Audience :: Developers
Classifier: Operating System :: OS Independent
Classifier: Programming Language :: JavaScript
Classifier: Programming Language :: Python :: 3 :: Only
Classifier: Programming Language :: Python :: 3.9
Classifier: Programming Language :: Python :: 3.10
Classifier: Programming Language :: Python :: 3.11
Classifier: Typing :: Typed
Classifier: Development Status :: 5 - Production/Stable
Classifier: License :: OSI Approved
Requires-Python: ~=3.9
License-File: LICENSE
Requires-Dist: aws-cdk-lib<3.0.0,>=2.156.0
Requires-Dist: constructs<11.0.0,>=10.0.5
Requires-Dist: gammarers.aws-secure-bucket<3.0.0,>=2.0.14
Requires-Dist: jsii<2.0.0,>=1.111.0
Requires-Dist: publication>=0.0.3
Requires-Dist: typeguard<4.3.0,>=2.13.3
